tssort/__init__.py
tssort/__main__.py
tssort/comparisons.txt
tssort/pairwise_ranking.py
tssort/sentences.txt
tssort-0.0.3.dist-info/METADATA
tssort-0.0.3.dist-info/WHEEL
tssort-0.0.3.dist-info/entry_points.txt
tssort-0.0.3.dist-info/licenses/LICENSE
tssort-0.0.3.dist-info/RECORD
