Metadata-Version: 2.4
Name: TSSort
Version: 0.0.3
Summary: A library and tool for implementing TSSort in Python, which allows for the sorting of a list using pairwise comparisons while accounting for noisy data.
Project-URL: Homepage, https://github.com/aconeil/TSSort
Author: Alexandra Fort, Daniel Swanson, Nicholas Howell
License-Expression: MIT
License-File: LICENSE
Keywords: pairwise,sort,tssort
Classifier: Programming Language :: Python
Classifier: Programming Language :: Python :: 3
Requires-Python: >=3.7
Requires-Dist: numpy>=1.24
Requires-Dist: scipy>=1.10.1
Provides-Extra: dev
Requires-Dist: bumpver; extra == 'dev'
Requires-Dist: pip-tools; extra == 'dev'
